Metadata-Version: 2.1
Name: odoo-addon-sale_discount_display_amount
Version: 18.0.1.0.0.2
Requires-Python: >=3.10
Requires-Dist: odoo==18.0.*
Summary: This addon intends to display the amount of the discount computed on sale_order_line and sale_order level
Home-page: https://github.com/OCA/sale-workflow
License: AGPL-3
Author: ACSONE SA/NV, Odoo Community Association (OCA)
Author-email: support@odoo-community.org
Classifier: Programming Language :: Python
Classifier: Framework :: Odoo
Classifier: Framework :: Odoo :: 18.0
Classifier: License :: OSI Approved :: GNU Affero General Public License v3
